README.md
setup.cfg
setup.py
mininf/__init__.py
mininf/core.py
mininf/distributions.py
mininf/nn.py
mininf/util.py
mininf.egg-info/PKG-INFO
mininf.egg-info/SOURCES.txt
mininf.egg-info/dependency_links.txt
mininf.egg-info/requires.txt
mininf.egg-info/top_level.txt
tests/test_core.py
tests/test_distributions.py
tests/test_mininf.py
tests/test_nn.py
tests/test_util.py