Metadata-Version: 2.1
Name: mininf
Version: 0.1
Summary: mininf is a minimal library to infer the parameters of probabilistic programs and make predictions
